Metadata-Version: 2.1
Name: senpython
Version: 0.0.5
Summary: Senpai is an esoteric programming language that is inspired by anime girls. Don't ask why I made this.
Home-page: https://github.com/4gboframram/Senpython
Author: 4gboframram
License: mit
Keywords: programming_language,esolang,senpai
Platform: UNKNOWN
Classifier: Development Status :: 4 - Beta
Classifier: Intended Audience :: Developers
Classifier: Topic :: Software Development :: Libraries :: Python Modules
Classifier: Programming Language :: Python :: 3.8
